{"is_source_file": true, "format": "TypeScript (TSX)", "description": "React component for a task item in a task management app, handling display, editing, completion toggling, and deletion of individual tasks.", "external_files": ["@/lib/api"], "external_methods": ["completeTask", "deleteTask", "uncompleteTask", "updateTask"], "published": [], "classes": [], "methods": [{"name": "TaskItem", "description": "React functional component rendering a task with controls for marking complete/incomplete, editing, and deleting."}, {"name": "toggleComplete", "description": "Asynchronously toggles the task's completion status by calling external API methods."}, {"name": "saveEdit", "description": "Saves task edits by calling external API and handles validation."}, {"name": "remove", "description": "Deletes the task after user confirmation."}], "calls": ["completeTask", "uncompleteTask", "updateTask", "deleteTask"], "search-terms": ["TaskItem", "React", "Task", "completeTask", "deleteTask", "updateTask", "Task editing", "task management component"], "state": 2, "file_id": 13, "knowledge_revision": 29, "git_revision": "", "ctags": [], "hash": "03c6d1647cbf67a4bb57cedbf68bfe9b", "format-version": 4, "code-base-name": "to_do_frontend", "filename": "to_do_frontend/src/components/TaskItem.tsx", "revision_history": [{"29": ""}]}